[{"categories":["tutorials"],"contents":"Who even blogs in 2024? I do. Let me give you a few reasons why I am blogging in 2024.\nHaving a personal journal Learning to express my ideas through writing Sharing useful information to the public Learning necessary tools such as Obsidian and Hugo ![[obsidianlogo.png]]\n","permalink":"https://localhost:1313/how-i-made-this-blog/","tags":["hugo","blog","obsidian"],"title":"How to Make a Blog Using Hugo and Obsidian"},{"categories":["life"],"contents":"A Tech bro with a girlfriend?? That\u0026rsquo;s impossible. However, at one point in time, I would like to say I broke this standard by having a girlfriend for 2 years! Now as a nerdy tech bro, I am often consumed with learning new tech stacks and building personal projects. How can a tech bro even maintain their life while keeping their girlfriend happy? Well let me tell you all about that! ! ","permalink":"https://localhost:1313/tech-bro-with-a-gf/","tags":["life"],"title":"Tech Bro with a GF??"},{"categories":["archives"],"contents":"","permalink":"https://localhost:1313/archives/","tags":null,"title":"Archives"},{"categories":null,"contents":"","permalink":"https://localhost:1313/search/search/","tags":null,"title":""}]